setup.py
numstudents/__init__.py
numstudents/numstudents.py
numstudents.egg-info/PKG-INFO
numstudents.egg-info/SOURCES.txt
numstudents.egg-info/dependency_links.txt
numstudents.egg-info/not-zip-safe
numstudents.egg-info/top_level.txt