Metadata-Version: 2.1
Name: numstudents
Version: 1.0
Summary: Takes student information like name, regno, marks and prints at end
Home-page: https://github.com/15Praveenreddy/sample
Author: Praveen_Reddy_Pullagurala
Author-email: 15praveenreddy@gmail.com
